[
  {
    "Page": 2,
    "Title": "B Minor Waltz",
    "Composer": "Bill Evans"
  },
  {
    "Page": 3,
    "Title": "Bill's Belli",
    "Composer": "Bill Evans"
  },
  {
    "Page": 4,
    "Title": "Bill's Hit Tune",
    "Composer": "Bill Evans"
  },
  {
    "Page": 6,
    "Title": "Blue In Green",
    "Composer": "Miles Davis"
  },
  {
    "Page": 7,
    "Title": "C Minor Blues Chase",
    "Composer": "Bill Evans"
  },
  {
    "Page": 8,
    "Title": "Carnival",
    "Composer": "Bill Evans"
  },
  {
    "Page": 10,
    "Title": "Catch The Wind",
    "Composer": "Bill Evans"
  },
  {
    "Page": 11,
    "Title": "Chromatic Tune",
    "Composer": "Bill Evans"
  },
  {
    "Page": 12,
    "Title": "Children's Play Song",
    "Composer": "Bill Evans"
  },
  {
    "Page": 14,
    "Title": "Comrade Conrad",
    "Composer": "Bill Evans"
  },
  {
    "Page": 15,
    "Title": "Displacement",
    "Composer": "Bill Evans"
  },
  {
    "Page": 16,
    "Title": "Epilogue",
    "Composer": "Bill Evans"
  },
  {
    "Page": 17,
    "Title": "Five",
    "Composer": "Bill Evans"
  },
  {
    "Page": 20,
    "Title": "In April",
    "Composer": "Bill Evans"
  },
  {
    "Page": 22,
    "Title": "For Nenette",
    "Composer": "Bill Evans"
  },
  {
    "Page": 23,
    "Title": "Fudgesicle Built For Four",
    "Composer": "Bill Evans"
  },
  {
    "Page": 26,
    "Title": "Fun Ride",
    "Composer": "Bill Evans"
  },
  {
    "Page": 28,
    "Title": "Funkallero",
    "Composer": "Bill Evans"
  },
  {
    "Page": 29,
    "Title": "Funny Man",
    "Composer": "Bill Evans"
  },
  {
    "Page": 30,
    "Title": "G Waltz",
    "Composer": "Bill Evans"
  },
  {
    "Page": 32,
    "Title": "Interplay",
    "Composer": "Bill Evans"
  },
  {
    "Page": 33,
    "Title": "It's Love - It's Christmas",
    "Composer": "Bill Evans"
  },
  {
    "Page": 34,
    "Title": "Knit For Mary F.",
    "Composer": "Bill Evans"
  },
  {
    "Page": 36,
    "Title": "Laurie (The Dream)",
    "Composer": "Bill Evans"
  },
  {
    "Page": 39,
    "Title": "Letter To Evan",
    "Composer": "Bill Evans"
  },
  {
    "Page": 42,
    "Title": "Maxine",
    "Composer": "Bill Evans"
  },
  {
    "Page": 44,
    "Title": "My Bells",
    "Composer": "Bill Evans"
  },
  {
    "Page": 46,
    "Title": "N.Y.C.'S No Lark",
    "Composer": "Bill Evans"
  },
  {
    "Page": 47,
    "Title": "One For Helen",
    "Composer": "Bill Evans"
  },
  {
    "Page": 48,
    "Title": "Only Child",
    "Composer": "Bill Evans"
  },
  {
    "Page": 50,
    "Title": "Opener (The)",
    "Composer": "Bill Evans"
  },
  {
    "Page": 51,
    "Title": "Orbit (Unless It's You)",
    "Composer": "Bill Evans"
  },
  {
    "Page": 52,
    "Title": "Peace Piece",
    "Composer": "Bill Evans"
  },
  {
    "Page": 53,
    "Title": "Perils Scope",
    "Composer": "Bill Evans"
  },
  {
    "Page": 54,
    "Title": "Prologue",
    "Composer": "Bill Evans"
  },
  {
    "Page": 56,
    "Title": "Quiet Now",
    "Composer": "Denny Zeitlin"
  },
  {
    "Page": 60,
    "Title": "Re: Person I Knew",
    "Composer": "Bill Evans"
  },
  {
    "Page": 62,
    "Title": "Show-Type Tune (Tune For",
    "Composer": "Bill Evans"
  },
  {
    "Page": 64,
    "Title": "Simple Matter Of Convictio",
    "Composer": "Bill Evans"
  },
  {
    "Page": 65,
    "Title": "Song For Helen",
    "Composer": "Bill Evans"
  },
  {
    "Page": 66,
    "Title": "Since We Met",
    "Composer": "Bill Evans"
  },
  {
    "Page": 68,
    "Title": "Story Line",
    "Composer": "Bill Evans"
  },
  {
    "Page": 70,
    "Title": "Theme (What You Gave)",
    "Composer": "Bill Evans"
  },
  {
    "Page": 71,
    "Title": "Then Came You",
    "Composer": "Bill Evans"
  },
  {
    "Page": 72,
    "Title": "These Things Called Chang",
    "Composer": "Bill Evans"
  },
  {
    "Page": 74,
    "Title": "Tiffany",
    "Composer": "Bill Evans"
  },
  {
    "Page": 76,
    "Title": "Time Remembered",
    "Composer": "Bill Evans"
  },
  {
    "Page": 78,
    "Title": "Turn Out The Stars",
    "Composer": "Bill Evans"
  },
  {
    "Page": 81,
    "Title": "Twelve Tone Tune (T.T.T.)",
    "Composer": "Bill Evans"
  },
  {
    "Page": 84,
    "Title": "Two Lonely People (The)",
    "Composer": "Bill Evans"
  },
  {
    "Page": 88,
    "Title": "Very Early",
    "Composer": "Bill Evans"
  },
  {
    "Page": 90,
    "Title": "Walkin' Up",
    "Composer": "Bill Evans"
  },
  {
    "Page": 91,
    "Title": "Waltz For Debby",
    "Composer": "Bill Evans"
  },
  {
    "Page": 96,
    "Title": "Waltz In Eb",
    "Composer": "Bill Evans"
  },
  {
    "Page": 97,
    "Title": "We Will Meet Again",
    "Composer": "Bill Evans"
  },
  {
    "Page": 98,
    "Title": "Yet Ne'er Broken",
    "Composer": "Bill Evans"
  },
  {
    "Page": 100,
    "Title": "Your Story",
    "Composer": "Bill Evans"
  }
]
